<?xml version="1.0" encoding="utf-8" ?>
<dwsync>
<file name="app.css" local="131440156830000000" remote="131443861420000000" testing="0" />
<file name="bootstrap-theme.css" local="131139211140000000" remote="131443861430000000" testing="0" />
<file name="bootstrap-theme.css.map" local="131139211140000000" remote="131443861450000000" testing="0" />
<file name="bootstrap-theme.min.css" local="131139211140000000" remote="131443861460000000" testing="0" />
<file name="bootstrap-theme.min.css.map" local="131139211140000000" remote="131443861470000000" testing="0" />
<file name="bootstrap.css" local="131139211140000000" remote="131443861490000000" testing="0" />
<file name="bootstrap.css.map" local="131139211140000000" remote="131443861540000000" testing="0" />
<file name="bootstrap.min.css" local="131139211140000000" remote="131443861550000000" testing="0" />
<file name="bootstrap.min.css.map" local="131139211140000000" remote="131443861600000000" testing="0" />
<file name="dashboard.css" local="131139211140000000" remote="131443861610000000" testing="0" />
<file name="ie10-viewport-bug-workaround.css" local="131139211140000000" remote="131443861620000000" testing="0" />
</dwsync>